pyabtest/__init__.py
pyabtest/binary_metric_test.py
pyabtest/numeric_metric_test.py
pyabtest/srm_test.py
pyabtest-0.3.dist-info/LICENSE
pyabtest-0.3.dist-info/METADATA
pyabtest-0.3.dist-info/WHEEL
pyabtest-0.3.dist-info/top_level.txt
pyabtest-0.3.dist-info/RECORD
