Metadata-Version: 2.1
Name: pyabtest
Version: 0.3
Summary: A simple tool to calculate P-value after conducting an A/B experiment
Home-page: https://github.com/ramab1988/pyabtest
Author: Rama Badrinath
Author-email: ramab1988@gmail.com
Project-URL: Bug Tracker, https://github.com/ramab1988/pyabtest/issues
Classifier: Programming Language :: Python :: 3
Classifier: License :: OSI Approved :: MIT License
Classifier: Operating System :: OS Independent
Requires-Python: >=3.6
License-File: LICENSE
Requires-Dist: numpy
Requires-Dist: scipy
Requires-Dist: sklearn
Requires-Dist: multiprocess
Requires-Dist: numba
